{"Modules":[{"Key":"dns","Source":"../dns","Dir":"../dns"},{"Key":"rds","Source":"../rds","Dir":"../rds"},{"Key":"elb","Source":"../elb","Dir":"../elb"},{"Key":"drs","Source":"../drs","Dir":"../drs"},{"Key":"dcs","Source":"../dcs","Dir":"../dcs"},{"Key":"ecs","Source":"../ecs","Dir":"../ecs"},{"Key":"","Source":"","Dir":"."},{"Key":"vpc_bangkok","Source":"../vpc","Dir":"../vpc"},{"Key":"sg","Source":"../sg","Dir":"../sg"},{"Key":"nat","Source":"../nat","Dir":"../nat"},{"Key":"vpc","Source":"../vpc","Dir":"../vpc"},{"Key":"vpn","Source":"../vpn","Dir":"../vpn"}]}